{
	"textures": [
		{
			"image": "sheet.png",
			"format": "RGBA8888",
			"size": {
				"w": 2008,
				"h": 1659
			},
			"scale": 1,
			"frames": [
				{
					"filename": "button.png",
					"rotated": false,
					"trimmed": true,
					"sourceSize": {
						"w": 366,
						"h": 100
					},
					"spriteSourceSize": {
						"x": 11,
						"y": 1,
						"w": 347,
						"h": 96
					},
					"frame": {
						"x": 1,
						"y": 1,
						"w": 347,
						"h": 96
					}
				},
				{
					"filename": "flip-part.png",
					"rotated": false,
					"trimmed": true,
					"sourceSize": {
						"w": 285,
						"h": 354
					},
					"spriteSourceSize": {
						"x": 35,
						"y": 27,
						"w": 223,
						"h": 171
					},
					"frame": {
						"x": 350,
						"y": 1,
						"w": 223,
						"h": 171
					}
				},
				{
					"filename": "garbage.png",
					"rotated": false,
					"trimmed": true,
					"sourceSize": {
						"w": 206,
						"h": 206
					},
					"spriteSourceSize": {
						"x": 10,
						"y": 10,
						"w": 186,
						"h": 186
					},
					"frame": {
						"x": 575,
						"y": 1,
						"w": 186,
						"h": 186
					}
				},
				{
					"filename": "glass.png",
					"rotated": false,
					"trimmed": true,
					"sourceSize": {
						"w": 206,
						"h": 206
					},
					"spriteSourceSize": {
						"x": 10,
						"y": 10,
						"w": 186,
						"h": 186
					},
					"frame": {
						"x": 763,
						"y": 1,
						"w": 186,
						"h": 186
					}
				},
				{
					"filename": "metal.png",
					"rotated": false,
					"trimmed": true,
					"sourceSize": {
						"w": 206,
						"h": 206
					},
					"spriteSourceSize": {
						"x": 10,
						"y": 10,
						"w": 186,
						"h": 186
					},
					"frame": {
						"x": 951,
						"y": 1,
						"w": 186,
						"h": 186
					}
				},
				{
					"filename": "paper.png",
					"rotated": false,
					"trimmed": true,
					"sourceSize": {
						"w": 206,
						"h": 206
					},
					"spriteSourceSize": {
						"x": 10,
						"y": 10,
						"w": 186,
						"h": 186
					},
					"frame": {
						"x": 1139,
						"y": 1,
						"w": 186,
						"h": 186
					}
				},
				{
					"filename": "plastic.png",
					"rotated": false,
					"trimmed": true,
					"sourceSize": {
						"w": 206,
						"h": 206
					},
					"spriteSourceSize": {
						"x": 10,
						"y": 10,
						"w": 186,
						"h": 186
					},
					"frame": {
						"x": 1327,
						"y": 1,
						"w": 186,
						"h": 186
					}
				},
				{
					"filename": "flip2-part.png",
					"rotated": false,
					"trimmed": true,
					"sourceSize": {
						"w": 400,
						"h": 400
					},
					"spriteSourceSize": {
						"x": 74,
						"y": 0,
						"w": 220,
						"h": 295
					},
					"frame": {
						"x": 1515,
						"y": 1,
						"w": 220,
						"h": 295
					}
				},
				{
					"filename": "flip.png",
					"rotated": false,
					"trimmed": false,
					"sourceSize": {
						"w": 500,
						"h": 679
					},
					"spriteSourceSize": {
						"x": 0,
						"y": 0,
						"w": 500,
						"h": 679
					},
					"frame": {
						"x": 1,
						"y": 174,
						"w": 500,
						"h": 679
					}
				},
				{
					"filename": "flip2.png",
					"rotated": false,
					"trimmed": false,
					"sourceSize": {
						"w": 500,
						"h": 679
					},
					"spriteSourceSize": {
						"x": 0,
						"y": 0,
						"w": 500,
						"h": 679
					},
					"frame": {
						"x": 503,
						"y": 189,
						"w": 500,
						"h": 679
					}
				},
				{
					"filename": "hold.png",
					"rotated": false,
					"trimmed": false,
					"sourceSize": {
						"w": 500,
						"h": 679
					},
					"spriteSourceSize": {
						"x": 0,
						"y": 0,
						"w": 500,
						"h": 679
					},
					"frame": {
						"x": 1005,
						"y": 189,
						"w": 500,
						"h": 679
					}
				},
				{
					"filename": "hold2.png",
					"rotated": false,
					"trimmed": false,
					"sourceSize": {
						"w": 500,
						"h": 679
					},
					"spriteSourceSize": {
						"x": 0,
						"y": 0,
						"w": 500,
						"h": 679
					},
					"frame": {
						"x": 1507,
						"y": 298,
						"w": 500,
						"h": 679
					}
				},
				{
					"filename": "left.png",
					"rotated": false,
					"trimmed": false,
					"sourceSize": {
						"w": 500,
						"h": 679
					},
					"spriteSourceSize": {
						"x": 0,
						"y": 0,
						"w": 500,
						"h": 679
					},
					"frame": {
						"x": 1,
						"y": 855,
						"w": 500,
						"h": 679
					}
				},
				{
					"filename": "right.png",
					"rotated": false,
					"trimmed": false,
					"sourceSize": {
						"w": 500,
						"h": 679
					},
					"spriteSourceSize": {
						"x": 0,
						"y": 0,
						"w": 500,
						"h": 679
					},
					"frame": {
						"x": 503,
						"y": 870,
						"w": 500,
						"h": 679
					}
				},
				{
					"filename": "straight.png",
					"rotated": false,
					"trimmed": false,
					"sourceSize": {
						"w": 500,
						"h": 679
					},
					"spriteSourceSize": {
						"x": 0,
						"y": 0,
						"w": 500,
						"h": 679
					},
					"frame": {
						"x": 1005,
						"y": 870,
						"w": 500,
						"h": 679
					}
				},
				{
					"filename": "two.png",
					"rotated": false,
					"trimmed": false,
					"sourceSize": {
						"w": 500,
						"h": 679
					},
					"spriteSourceSize": {
						"x": 0,
						"y": 0,
						"w": 500,
						"h": 679
					},
					"frame": {
						"x": 1507,
						"y": 979,
						"w": 500,
						"h": 679
					}
				}
			]
		}
	],
	"meta": {
		"app": "https://www.codeandweb.com/texturepacker",
		"version": "3.0",
		"smartupdate": "$TexturePacker:SmartUpdate:8167fa8cbda75c71264ecd2fd293a3f2:7874fb8675ef14bfd0c123b064182bc7:9c44ecd7e9a522007eaff2949095bc1d$"
	}
}
